geomaneuvers/__init__.py
geomaneuvers/common.py
geomaneuvers/geomaneuvers.py
geomaneuvers-0.0.2.dist-info/LICENSE
geomaneuvers-0.0.2.dist-info/METADATA
geomaneuvers-0.0.2.dist-info/WHEEL
geomaneuvers-0.0.2.dist-info/top_level.txt
geomaneuvers-0.0.2.dist-info/RECORD
