Metadata-Version: 2.1
Name: geomaneuvers
Version: 0.0.2
Summary: A python package for maneuvering geospatial data from one form to another
Home-page: https://github.com/Dhirajx15/geomaneuvers
Author: Dhiraj Kumar
Author-email: dhiraj@mlinfomap.com
License: MIT license
Keywords: geomaneuvers
Classifier: Intended Audience :: Developers
Classifier: License :: OSI Approved :: MIT License
Classifier: Natural Language :: English
Classifier: Programming Language :: Python :: 3
Classifier: Programming Language :: Python :: 3.8
Classifier: Programming Language :: Python :: 3.9
Classifier: Programming Language :: Python :: 3.10
Classifier: Programming Language :: Python :: 3.11
Requires-Python: >=3.8
License-File: LICENSE
